excel_breaker/__init__.py
excel_breaker/excelBreaker.py
webengage_excel_breaker-0.1.0.dist-info/METADATA
webengage_excel_breaker-0.1.0.dist-info/WHEEL
webengage_excel_breaker-0.1.0.dist-info/entry_points.txt
webengage_excel_breaker-0.1.0.dist-info/top_level.txt
webengage_excel_breaker-0.1.0.dist-info/RECORD
