Metadata-Version: 2.4
Name: webengage-excel-breaker
Version: 0.1.0
Summary: Webengage internal tool to split Excel or CSV files multiple tabs into separate CSV files with streaming support
Home-page: https://www.webengage.com/
Author: Nipun Patel
Author-email: nipunp27@gmail.com
License: MIT
Classifier: Programming Language :: Python :: 3
Classifier: License :: OSI Approved :: MIT License
Classifier: Operating System :: OS Independent
Requires-Python: >=3.6
Requires-Dist: openpyxl>=3.1.2
Dynamic: author
Dynamic: author-email
Dynamic: classifier
Dynamic: description
Dynamic: description-content-type
Dynamic: home-page
Dynamic: license
Dynamic: requires-dist
Dynamic: requires-python
Dynamic: summary
